{
  "accuracy": 0.0,
  "pp": 10,
  "priority": 0,
  "power": 0,
  "effects": {
    "effect": "Prevents any Pokémon on the opposing side of the field from using any move the user knows until the user leaves the field.  This effect is live; if the user obtains new moves while on the field, these moves become restricted.  If no opposing Pokémon knows any of the user's moves when this move is used, this move will fail.",
    "shortEffect": "Prevents the target from using any moves that the user also knows."
  },
  "ailment": "none",
  "category": "unique",
  "minHits": 0,
  "maxHits": 0,
  "minTurns": 0,
  "maxTurns": 0,
  "drainRecoil": 0,
  "healing": 0,
  "critRate": 0,
  "ailmentChance": 0.0,
  "flinchChance": 0.0,
  "statChance": 0.0,
  "statChanges": {},
  "targets": "user",
  "moveType": "psychic",
  "moveDescription": "If opposing Pokémon know any move also known by\nthe user, they are prevented from using it.",
  "moveName": "Imprison",
  "id": 286
}