{
  "pokemonName": "Chansey",
  "pokedexNumber": 113,
  "pokedexDescription": "Chansey lays nutritionally excellent eggs on an everyday basis.\nThe eggs are so delicious, they are easily and eagerly\ndevoured by even those people who have lost their appetite.",
  "baseHP": 250,
  "baseAttack": 5,
  "baseDefense": 5,
  "baseSpecialAttack": 35,
  "baseSpecialDefense": 105,
  "baseSpeed": 50,
  "types": [
    "normal"
  ],
  "evolvesFrom": null,
  "evolutionInfo": {
    "speciesName": "Chansey",
    "evolvesTo": {
      "Blissey": {
        "itemUsed": "",
        "gender": "genderless",
        "heldItemName": "",
        "knownMoveName": "",
        "knownMoveType": "null",
        "minLevel": 0,
        "minHappiness": 220,
        "minBeauty": 0,
        "minAffection": 0,
        "mustBeRaining": false,
        "partyPokemonRequired": "",
        "partyPokemonWithTypeRequired": "null",
        "relativePhysicalStats": 999,
        "timeOfDay": null,
        "mustBeTraded": false,
        "evolves": false
      }
    },
    "isBaby": false,
    "triggers": {
      "itemUsed": "",
      "gender": "genderless",
      "heldItemName": "Oval Stone",
      "knownMoveName": "",
      "knownMoveType": "null",
      "minLevel": 0,
      "minHappiness": 0,
      "minBeauty": 0,
      "minAffection": 0,
      "mustBeRaining": false,
      "partyPokemonRequired": "",
      "partyPokemonWithTypeRequired": "null",
      "relativePhysicalStats": 999,
      "timeOfDay": null,
      "mustBeTraded": false,
      "evolves": false
    },
    "id": 51
  },
  "baseExperience": 395,
  "genderRateRaw": 1.024,
  "captureRateRaw": 30.0,
  "baseHappiness": 140,
  "hatchCounter": 40,
  "hasMultipleForms": false,
  "growthRate": "fast",
  "eggGroups": [
    "fairy"
  ],
  "learnableMoves": {
    "LevelUp": {
      "Pound": 1,
      "Double Slap": 12,
      "Mega Punch": 0,
      "Fire Punch": 0,
      "Ice Punch": 0,
      "Thunder Punch": 0,
      "Mega Kick": 0,
      "Headbutt": 0,
      "Body Slam": 0,
      "Take Down": 27,
      "Double Edge": 65,
      "Tail Whip": 5,
      "Growl": 1,
      "Sing": 31,
      "Water Gun": 0,
      "Bubble Beam": 0,
      "Submission": 0,
      "Strength": 0,
      "Rage": 0,
      "Teleport": 0,
      "Mimic": 0,
      "Minimize": 23,
      "Defense Curl": 1,
      "Reflect": 0,
      "Bide": 0,
      "Egg Bomb": 44,
      "Skull Bash": 0,
      "Soft Boiled": 16,
      "Flash": 0,
      "Psywave": 0,
      "Tri Attack": 0,
      "Snore": 0,
      "Curse": 0,
      "Mud Slap": 0,
      "Zap Cannon": 0,
      "Icy Wind": 0,
      "Rollout": 0,
      "Dynamic Punch": 0,
      "Iron Tail": 0,
      "Rock Smash": 0,
      "Focus Punch": 0,
      "Recycle": 0,
      "Endeavor": 0,
      "Skill Swap": 0,
      "Refresh": 9,
      "Snatch": 0,
      "Secret Power": 0,
      "Hyper Voice": 0,
      "Covet": 0,
      "Shock Wave": 0,
      "Water Pulse": 0,
      "Healing Wish": 57,
      "Last Resort": 0,
      "Drain Punch": 0,
      "Zen Headbutt": 0,
      "Rock Climb": 0,
      "Captivate": 0,
      "Stealth Rock": 0,
      "Heal Pulse": 39,
      "Incinerate": 0,
      "Retaliate": 0,
      "Bestow": 20,
      "Power Up Punch": 0
    },
    "Egg": {
      "Counter": 0,
      "Seismic Toss": 0,
      "Metronome": 0,
      "Endure": 0,
      "Heal Bell": 0,
      "Present": 0,
      "Helping Hand": 0,
      "Aromatherapy": 0,
      "Gravity": 0,
      "Natural Gift": 0,
      "Mud Bomb": 0
    },
    "Tutor": {},
    "Machine": {
      "Flamethrower": 0,
      "Ice Beam": 0,
      "Blizzard": 0,
      "Hyper Beam": 0,
      "Solar Beam": 0,
      "Thunderbolt": 0,
      "Thunder Wave": 0,
      "Thunder": 0,
      "Earthquake": 0,
      "Toxic": 0,
      "Psychic": 0,
      "Double Team": 0,
      "Light Screen": 0,
      "Fire Blast": 0,
      "Dream Eater": 0,
      "Rest": 0,
      "Rock Slide": 0,
      "Substitute": 0,
      "Protect": 0,
      "Sandstorm": 0,
      "Swagger": 0,
      "Attract": 0,
      "Sleep Talk": 0,
      "Return": 0,
      "Frustration": 0,
      "Safeguard": 0,
      "Hidden Power": 0,
      "Rain Dance": 0,
      "Sunny Day": 0,
      "Psych Up": 0,
      "Shadow Ball": 0,
      "Hail": 0,
      "Facade": 0,
      "Brick Break": 0,
      "Rock Tomb": 0,
      "Calm Mind": 0,
      "Fling": 0,
      "Giga Impact": 0,
      "Grass Knot": 0,
      "Charge Beam": 0,
      "Round": 0,
      "Echoed Voice": 0,
      "Bulldoze": 0,
      "Work Up": 0,
      "Wild Charge": 0,
      "Confide": 0,
      "Dazzling Gleam": 0
    }
  }
}