{
  "pokemonName": "Staryu",
  "pokedexNumber": 120,
  "pokedexDescription": "Staryu’s center section has an organ called the core that\nshines bright red. If you go to a beach toward the end of\nsummer, the glowing cores of these Pokémon look like the\nstars in the sky.",
  "baseHP": 30,
  "baseAttack": 45,
  "baseDefense": 55,
  "baseSpecialAttack": 70,
  "baseSpecialDefense": 55,
  "baseSpeed": 85,
  "types": [
    "water"
  ],
  "evolvesFrom": null,
  "evolutionInfo": {
    "speciesName": "Staryu",
    "evolvesTo": {
      "Starmie": {
        "itemUsed": "Water Stone",
        "gender": "genderless",
        "heldItemName": "",
        "knownMoveName": "",
        "knownMoveType": "null",
        "minLevel": 0,
        "minHappiness": 0,
        "minBeauty": 0,
        "minAffection": 0,
        "mustBeRaining": false,
        "partyPokemonRequired": "",
        "partyPokemonWithTypeRequired": "null",
        "relativePhysicalStats": 999,
        "timeOfDay": null,
        "mustBeTraded": false,
        "evolves": false
      }
    },
    "isBaby": false,
    "triggers": {
      "itemUsed": null,
      "gender": "null",
      "heldItemName": null,
      "knownMoveName": null,
      "knownMoveType": "null",
      "minLevel": 0,
      "minHappiness": 0,
      "minBeauty": 0,
      "minAffection": 0,
      "mustBeRaining": false,
      "partyPokemonRequired": null,
      "partyPokemonWithTypeRequired": "null",
      "relativePhysicalStats": 0,
      "timeOfDay": null,
      "mustBeTraded": false,
      "evolves": false
    },
    "id": 56
  },
  "baseExperience": 68,
  "genderRateRaw": -1.0,
  "captureRateRaw": 225.0,
  "baseHappiness": 70,
  "hatchCounter": 20,
  "hasMultipleForms": false,
  "growthRate": "slow",
  "eggGroups": [
    "water3"
  ],
  "learnableMoves": {
    "LevelUp": {
      "Tackle": 1,
      "Take Down": 0,
      "Double Edge": 0,
      "Supersonic": 0,
      "Water Gun": 4,
      "Hydro Pump": 53,
      "Bubble Beam": 18,
      "Aurora Beam": 0,
      "Rage": 0,
      "Teleport": 0,
      "Mimic": 0,
      "Recover": 10,
      "Harden": 1,
      "Minimize": 31,
      "Confuse Ray": 40,
      "Barrier": 0,
      "Bide": 0,
      "Swift": 16,
      "Skull Bash": 0,
      "Flash": 0,
      "Psywave": 13,
      "Tri Attack": 0,
      "Snore": 0,
      "Curse": 0,
      "Zap Cannon": 0,
      "Icy Wind": 0,
      "Endure": 0,
      "Rollout": 0,
      "Attract": 0,
      "Pain Split": 0,
      "Rapid Spin": 7,
      "Twister": 0,
      "Whirlpool": 0,
      "Magic Coat": 0,
      "Recycle": 0,
      "Secret Power": 0,
      "Dive": 0,
      "Camouflage": 22,
      "Cosmic Power": 49,
      "Signal Beam": 0,
      "Water Pulse": 0,
      "Gravity": 0,
      "Brine": 28,
      "Natural Gift": 0,
      "Power Gem": 37,
      "Reflect Type": 35
    },
    "Egg": {},
    "Tutor": {},
    "Machine": {
      "Surf": 0,
      "Ice Beam": 0,
      "Blizzard": 0,
      "Thunderbolt": 0,
      "Thunder Wave": 0,
      "Thunder": 0,
      "Toxic": 0,
      "Psychic": 0,
      "Double Team": 0,
      "Light Screen": 0,
      "Reflect": 0,
      "Waterfall": 0,
      "Rest": 0,
      "Substitute": 0,
      "Protect": 0,
      "Swagger": 0,
      "Sleep Talk": 0,
      "Return": 0,
      "Frustration": 0,
      "Hidden Power": 0,
      "Rain Dance": 0,
      "Psych Up": 0,
      "Hail": 0,
      "Facade": 0,
      "Gyro Ball": 0,
      "Flash Cannon": 0,
      "Round": 0,
      "Scald": 0,
      "Confide": 0,
      "Dazzling Gleam": 0
    }
  }
}