{
  "pokemonName": "Mr Mime",
  "pokedexNumber": 122,
  "pokedexDescription": "Mr. Mime is a master of pantomime. Its gestures and motions\nconvince watchers that something unseeable actually exists.\nOnce the watchers are convinced, the unseeable thing exists\nas if it were real.",
  "baseHP": 40,
  "baseAttack": 45,
  "baseDefense": 65,
  "baseSpecialAttack": 100,
  "baseSpecialDefense": 120,
  "baseSpeed": 90,
  "types": [
    "fairy",
    "psychic"
  ],
  "evolvesFrom": null,
  "evolutionInfo": {
    "speciesName": "Mr Mime",
    "evolvesTo": {},
    "isBaby": false,
    "triggers": {
      "itemUsed": "",
      "gender": "genderless",
      "heldItemName": "",
      "knownMoveName": "Mimic",
      "knownMoveType": "null",
      "minLevel": 0,
      "minHappiness": 0,
      "minBeauty": 0,
      "minAffection": 0,
      "mustBeRaining": false,
      "partyPokemonRequired": "",
      "partyPokemonWithTypeRequired": "null",
      "relativePhysicalStats": 999,
      "timeOfDay": null,
      "mustBeTraded": false,
      "evolves": false
    },
    "id": 57
  },
  "baseExperience": 161,
  "genderRateRaw": 0.512,
  "captureRateRaw": 45.0,
  "baseHappiness": 70,
  "hatchCounter": 25,
  "hasMultipleForms": false,
  "growthRate": "medium",
  "eggGroups": [
    "humanshape"
  ],
  "learnableMoves": {
    "LevelUp": {
      "Pound": 1,
      "Double Slap": 11,
      "Mega Punch": 0,
      "Fire Punch": 0,
      "Ice Punch": 0,
      "Thunder Punch": 0,
      "Mega Kick": 0,
      "Headbutt": 0,
      "Body Slam": 0,
      "Take Down": 0,
      "Double Edge": 0,
      "Psybeam": 25,
      "Submission": 0,
      "Counter": 0,
      "Seismic Toss": 0,
      "Confusion": 1,
      "Meditate": 8,
      "Rage": 0,
      "Teleport": 0,
      "Barrier": 1,
      "Bide": 0,
      "Metronome": 0,
      "Skull Bash": 0,
      "Flash": 0,
      "Psywave": 15,
      "Nightmare": 0,
      "Snore": 0,
      "Curse": 0,
      "Mud Slap": 0,
      "Zap Cannon": 0,
      "Endure": 0,
      "Dynamic Punch": 0,
      "Baton Pass": 46,
      "Encore": 18,
      "Focus Punch": 0,
      "Helping Hand": 0,
      "Trick": 36,
      "Role Play": 43,
      "Magic Coat": 0,
      "Recycle": 32,
      "Skill Swap": 0,
      "Snatch": 0,
      "Secret Power": 0,
      "Signal Beam": 0,
      "Iron Defense": 0,
      "Covet": 0,
      "Magical Leaf": 1,
      "Shock Wave": 0,
      "Natural Gift": 0,
      "Copycat": 4,
      "Power Swap": 1,
      "Guard Swap": 1,
      "Drain Punch": 0,
      "Zen Headbutt": 0,
      "Captivate": 0,
      "Wide Guard": 1,
      "Wonder Room": 0,
      "Telekinesis": 0,
      "Foul Play": 0,
      "Quick Guard": 1,
      "Misty Terrain": 1,
      "Power Up Punch": 0
    },
    "Egg": {
      "Hypnosis": 0,
      "Mimic": 0,
      "Confuse Ray": 0,
      "Icy Wind": 0,
      "Future Sight": 0,
      "Fake Out": 0,
      "Teeter Dance": 0,
      "Wake Up Slap": 0,
      "Nasty Plot": 0,
      "Power Split": 0,
      "Magic Room": 0,
      "Psychic Terrain": 0
    },
    "Tutor": {},
    "Machine": {
      "Hyper Beam": 0,
      "Solar Beam": 0,
      "Thunderbolt": 0,
      "Thunder Wave": 0,
      "Thunder": 0,
      "Toxic": 0,
      "Psychic": 0,
      "Double Team": 0,
      "Light Screen": 0,
      "Reflect": 0,
      "Dream Eater": 0,
      "Rest": 0,
      "Substitute": 0,
      "Thief": 0,
      "Protect": 0,
      "Swagger": 0,
      "Attract": 0,
      "Sleep Talk": 0,
      "Return": 0,
      "Frustration": 0,
      "Safeguard": 0,
      "Hidden Power": 0,
      "Rain Dance": 0,
      "Sunny Day": 0,
      "Psych Up": 0,
      "Shadow Ball": 0,
      "Torment": 0,
      "Facade": 0,
      "Taunt": 0,
      "Brick Break": 0,
      "Aerial Ace": 0,
      "Calm Mind": 0,
      "Payback": 0,
      "Fling": 0,
      "Focus Blast": 0,
      "Energy Ball": 0,
      "Giga Impact": 0,
      "Trick Room": 0,
      "Grass Knot": 0,
      "Charge Beam": 0,
      "Psyshock": 0,
      "Round": 0,
      "Confide": 0,
      "Dazzling Gleam": 0,
      "Infestation": 0
    }
  }
}