{
  "pokemonName": "Yanma",
  "pokedexNumber": 193,
  "pokedexDescription": "Yanma is capable of seeing 360 degrees without having to\nmove its eyes. It is a great flier that is adept at making sudden\nstops and turning midair. This Pokémon uses its flying ability to\nquickly chase down targeted prey.",
  "baseHP": 65,
  "baseAttack": 65,
  "baseDefense": 45,
  "baseSpecialAttack": 75,
  "baseSpecialDefense": 45,
  "baseSpeed": 95,
  "types": [
    "flying",
    "bug"
  ],
  "evolvesFrom": null,
  "evolutionInfo": {
    "speciesName": "Yanma",
    "evolvesTo": {
      "Yanmega": {
        "itemUsed": "",
        "gender": "genderless",
        "heldItemName": "",
        "knownMoveName": "Ancient Power",
        "knownMoveType": "null",
        "minLevel": 0,
        "minHappiness": 0,
        "minBeauty": 0,
        "minAffection": 0,
        "mustBeRaining": false,
        "partyPokemonRequired": "",
        "partyPokemonWithTypeRequired": "null",
        "relativePhysicalStats": 999,
        "timeOfDay": null,
        "mustBeTraded": false,
        "evolves": false
      }
    },
    "isBaby": false,
    "triggers": {
      "itemUsed": null,
      "gender": "null",
      "heldItemName": null,
      "knownMoveName": null,
      "knownMoveType": "null",
      "minLevel": 0,
      "minHappiness": 0,
      "minBeauty": 0,
      "minAffection": 0,
      "mustBeRaining": false,
      "partyPokemonRequired": null,
      "partyPokemonWithTypeRequired": "null",
      "relativePhysicalStats": 0,
      "timeOfDay": null,
      "mustBeTraded": false,
      "evolves": false
    },
    "id": 95
  },
  "baseExperience": 78,
  "genderRateRaw": 0.512,
  "captureRateRaw": 75.0,
  "baseHappiness": 70,
  "hatchCounter": 20,
  "hasMultipleForms": false,
  "growthRate": "medium",
  "eggGroups": [
    "bug"
  ],
  "learnableMoves": {
    "LevelUp": {
      "Wing Attack": 43,
      "Headbutt": 0,
      "Tackle": 1,
      "Supersonic": 22,
      "Sonic Boom": 14,
      "String Shot": 0,
      "Hypnosis": 38,
      "Quick Attack": 6,
      "Mimic": 0,
      "Screech": 46,
      "Swift": 0,
      "Flash": 0,
      "Snore": 0,
      "Curse": 0,
      "Foresight": 1,
      "Detect": 17,
      "Giga Drain": 0,
      "Endure": 0,
      "Ancient Power": 33,
      "Uproar": 27,
      "Air Cutter": 0,
      "Natural Gift": 0,
      "Tailwind": 0,
      "Air Slash": 54,
      "Bug Buzz": 57,
      "Defog": 0,
      "Captivate": 0,
      "Bug Bite": 0,
      "Ominous Wind": 0
    },
    "Egg": {
      "Whirlwind": 0,
      "Double Edge": 0,
      "Leech Life": 0,
      "Reversal": 0,
      "Feint Attack": 0,
      "Pursuit": 0,
      "Secret Power": 0,
      "Silver Wind": 0,
      "Signal Beam": 0,
      "Feint": 0
    },
    "Tutor": {},
    "Machine": {
      "Solar Beam": 0,
      "Toxic": 0,
      "Psychic": 0,
      "Double Team": 0,
      "Dream Eater": 0,
      "Rest": 0,
      "Substitute": 0,
      "Thief": 0,
      "Protect": 0,
      "Swagger": 0,
      "Steel Wing": 0,
      "Attract": 0,
      "Sleep Talk": 0,
      "Return": 0,
      "Frustration": 0,
      "Hidden Power": 0,
      "Sunny Day": 0,
      "Shadow Ball": 0,
      "Facade": 0,
      "Aerial Ace": 0,
      "Roost": 0,
      "U Turn": 0,
      "Round": 0,
      "Confide": 0
    },
    "LightBallEgg": {}
  }
}