{
  "pokemonName": "Treecko",
  "pokedexNumber": 252,
  "pokedexDescription": "Treecko has small hooks on the bottom of its feet that enable\nit to scale vertical walls. This Pokémon attacks by slamming\nfoes with its thick tail.",
  "baseHP": 40,
  "baseAttack": 45,
  "baseDefense": 35,
  "baseSpecialAttack": 65,
  "baseSpecialDefense": 55,
  "baseSpeed": 70,
  "types": [
    "grass"
  ],
  "evolvesFrom": null,
  "evolutionInfo": {
    "speciesName": "Treecko",
    "evolvesTo": {
      "Grovyle": {
        "itemUsed": "",
        "gender": "genderless",
        "heldItemName": "",
        "knownMoveName": "",
        "knownMoveType": "null",
        "minLevel": 16,
        "minHappiness": 0,
        "minBeauty": 0,
        "minAffection": 0,
        "mustBeRaining": false,
        "partyPokemonRequired": "",
        "partyPokemonWithTypeRequired": "null",
        "relativePhysicalStats": 999,
        "timeOfDay": null,
        "mustBeTraded": false,
        "evolves": false
      }
    },
    "isBaby": false,
    "triggers": {
      "itemUsed": null,
      "gender": "null",
      "heldItemName": null,
      "knownMoveName": null,
      "knownMoveType": "null",
      "minLevel": 0,
      "minHappiness": 0,
      "minBeauty": 0,
      "minAffection": 0,
      "mustBeRaining": false,
      "partyPokemonRequired": null,
      "partyPokemonWithTypeRequired": "null",
      "relativePhysicalStats": 0,
      "timeOfDay": null,
      "mustBeTraded": false,
      "evolves": false
    },
    "id": 130
  },
  "baseExperience": 62,
  "genderRateRaw": 0.128,
  "captureRateRaw": 45.0,
  "baseHappiness": 70,
  "hatchCounter": 20,
  "hasMultipleForms": false,
  "growthRate": "mediumSlow",
  "eggGroups": [
    "dragon",
    "monster"
  ],
  "learnableMoves": {
    "LevelUp": {
      "Pound": 1,
      "Mega Punch": 0,
      "Thunder Punch": 0,
      "Cut": 0,
      "Slam": 29,
      "Mega Kick": 0,
      "Headbutt": 0,
      "Body Slam": 0,
      "Double Edge": 0,
      "Leer": 1,
      "Low Kick": 0,
      "Counter": 0,
      "Seismic Toss": 0,
      "Strength": 0,
      "Absorb": 5,
      "Mega Drain": 13,
      "Dig": 0,
      "Agility": 25,
      "Quick Attack": 9,
      "Mimic": 0,
      "Screech": 49,
      "Swift": 0,
      "Flash": 0,
      "Snore": 0,
      "Mud Slap": 0,
      "Detect": 33,
      "Giga Drain": 21,
      "Endure": 0,
      "Fury Cutter": 0,
      "Dynamic Punch": 0,
      "Pursuit": 17,
      "Iron Tail": 0,
      "Rock Smash": 0,
      "Focus Punch": 0,
      "Secret Power": 0,
      "Seed Bomb": 0,
      "Drain Punch": 0,
      "Captivate": 0,
      "Quick Guard": 41,
      "Power Up Punch": 0
    },
    "Egg": {
      "Razor Wind": 0,
      "Double Kick": 0,
      "Leech Seed": 0,
      "Dragon Breath": 0,
      "Synthesis": 0,
      "Crunch": 0,
      "Endeavor": 0,
      "Mud Sport": 0,
      "Crush Claw": 0,
      "Grass Whistle": 0,
      "Bullet Seed": 0,
      "Magical Leaf": 0,
      "Natural Gift": 0,
      "Worry Seed": 0,
      "Leaf Storm": 0,
      "Grassy Terrain": 0
    },
    "Tutor": {
      "Grass Pledge": 0
    },
    "Machine": {
      "Swords Dance": 0,
      "Solar Beam": 0,
      "Toxic": 0,
      "Double Team": 0,
      "Rest": 0,
      "Rock Slide": 0,
      "Substitute": 0,
      "Protect": 0,
      "Swagger": 0,
      "Attract": 0,
      "Sleep Talk": 0,
      "Return": 0,
      "Frustration": 0,
      "Safeguard": 0,
      "Hidden Power": 0,
      "Sunny Day": 0,
      "Facade": 0,
      "Nature Power": 0,
      "Brick Break": 0,
      "Rock Tomb": 0,
      "Aerial Ace": 0,
      "Fling": 0,
      "Energy Ball": 0,
      "Grass Knot": 0,
      "Round": 0,
      "Acrobatics": 0,
      "Work Up": 0,
      "Confide": 0
    },
    "LightBallEgg": {}
  }
}