{
  "pokemonName": "Poliwhirl",
  "pokedexNumber": 61,
  "pokedexDescription": "The surface of Poliwhirl’s body is always wet and slick with\na slimy fluid. Because of this slippery covering, it can easily\nslip and slide out of the clutches of any enemy in battle.",
  "baseHP": 65,
  "baseAttack": 65,
  "baseDefense": 65,
  "baseSpecialAttack": 50,
  "baseSpecialDefense": 50,
  "baseSpeed": 90,
  "types": [
    "water"
  ],
  "evolvesFrom": null,
  "evolutionInfo": {
    "speciesName": "Poliwhirl",
    "evolvesTo": {
      "Poliwrath": {
        "itemUsed": "Water Stone",
        "gender": "genderless",
        "heldItemName": "",
        "knownMoveName": "",
        "knownMoveType": "null",
        "minLevel": 0,
        "minHappiness": 0,
        "minBeauty": 0,
        "minAffection": 0,
        "mustBeRaining": false,
        "partyPokemonRequired": "",
        "partyPokemonWithTypeRequired": "null",
        "relativePhysicalStats": 999,
        "timeOfDay": null,
        "mustBeTraded": false,
        "evolves": false
      },
      "Politoed": {
        "itemUsed": "",
        "gender": "genderless",
        "heldItemName": "Kings Rock",
        "knownMoveName": "",
        "knownMoveType": "null",
        "minLevel": 0,
        "minHappiness": 0,
        "minBeauty": 0,
        "minAffection": 0,
        "mustBeRaining": false,
        "partyPokemonRequired": "",
        "partyPokemonWithTypeRequired": "null",
        "relativePhysicalStats": 999,
        "timeOfDay": null,
        "mustBeTraded": false,
        "evolves": false
      }
    },
    "isBaby": false,
    "triggers": {
      "itemUsed": "",
      "gender": "genderless",
      "heldItemName": "",
      "knownMoveName": "",
      "knownMoveType": "null",
      "minLevel": 25,
      "minHappiness": 0,
      "minBeauty": 0,
      "minAffection": 0,
      "mustBeRaining": false,
      "partyPokemonRequired": "",
      "partyPokemonWithTypeRequired": "null",
      "relativePhysicalStats": 999,
      "timeOfDay": null,
      "mustBeTraded": false,
      "evolves": false
    },
    "id": 26
  },
  "baseExperience": 135,
  "genderRateRaw": 0.512,
  "captureRateRaw": 120.0,
  "baseHappiness": 70,
  "hatchCounter": 20,
  "hasMultipleForms": false,
  "growthRate": "mediumSlow",
  "eggGroups": [
    "water1"
  ],
  "learnableMoves": {
    "LevelUp": {
      "Double Slap": 15,
      "Mega Punch": 0,
      "Ice Punch": 0,
      "Mega Kick": 0,
      "Headbutt": 0,
      "Body Slam": 21,
      "Take Down": 0,
      "Double Edge": 0,
      "Water Gun": 5,
      "Hydro Pump": 48,
      "Bubble Beam": 27,
      "Submission": 0,
      "Counter": 0,
      "Seismic Toss": 0,
      "Strength": 0,
      "Fissure": 0,
      "Dig": 0,
      "Hypnosis": 8,
      "Rage": 0,
      "Mimic": 0,
      "Defense Curl": 0,
      "Bide": 0,
      "Metronome": 0,
      "Skull Bash": 0,
      "Amnesia": 0,
      "Bubble": 11,
      "Psywave": 0,
      "Snore": 0,
      "Curse": 0,
      "Belly Drum": 37,
      "Mud Slap": 0,
      "Icy Wind": 0,
      "Detect": 0,
      "Endure": 0,
      "Rock Smash": 0,
      "Whirlpool": 0,
      "Focus Punch": 0,
      "Helping Hand": 0,
      "Endeavor": 0,
      "Secret Power": 0,
      "Dive": 0,
      "Mud Shot": 32,
      "Water Sport": 1,
      "Water Pulse": 0,
      "Wake Up Slap": 43,
      "Natural Gift": 0,
      "Mud Bomb": 53,
      "Captivate": 0,
      "Power Up Punch": 0
    },
    "Egg": {},
    "Tutor": {},
    "Machine": {
      "Surf": 0,
      "Ice Beam": 0,
      "Blizzard": 0,
      "Earthquake": 0,
      "Toxic": 0,
      "Psychic": 0,
      "Double Team": 0,
      "Waterfall": 0,
      "Rest": 0,
      "Substitute": 0,
      "Thief": 0,
      "Protect": 0,
      "Swagger": 0,
      "Attract": 0,
      "Sleep Talk": 0,
      "Return": 0,
      "Frustration": 0,
      "Hidden Power": 0,
      "Rain Dance": 0,
      "Hail": 0,
      "Facade": 0,
      "Brick Break": 0,
      "Fling": 0,
      "Round": 0,
      "Scald": 0,
      "Bulldoze": 0,
      "Confide": 0
    }
  }
}