{
  "pokemonName": "Squirtle",
  "pokedexNumber": 7,
  "pokedexDescription": "Squirtle’s shell is not merely used for protection.\nThe shell’s rounded shape and the grooves on its surface\nhelp minimize resistance in water, enabling this Pokémon\nto swim at high speeds.",
  "baseHP": 44,
  "baseAttack": 48,
  "baseDefense": 65,
  "baseSpecialAttack": 50,
  "baseSpecialDefense": 64,
  "baseSpeed": 43,
  "types": [
    "water"
  ],
  "evolvesFrom": null,
  "evolutionInfo": {
    "speciesName": "Squirtle",
    "evolvesTo": {
      "Wartortle": {
        "itemUsed": "",
        "gender": "genderless",
        "heldItemName": "",
        "knownMoveName": "",
        "knownMoveType": "null",
        "minLevel": 16,
        "minHappiness": 0,
        "minBeauty": 0,
        "minAffection": 0,
        "mustBeRaining": false,
        "partyPokemonRequired": "",
        "partyPokemonWithTypeRequired": "null",
        "relativePhysicalStats": 999,
        "timeOfDay": null,
        "mustBeTraded": false,
        "evolves": false
      }
    },
    "isBaby": false,
    "triggers": {
      "itemUsed": null,
      "gender": "null",
      "heldItemName": null,
      "knownMoveName": null,
      "knownMoveType": "null",
      "minLevel": 0,
      "minHappiness": 0,
      "minBeauty": 0,
      "minAffection": 0,
      "mustBeRaining": false,
      "partyPokemonRequired": null,
      "partyPokemonWithTypeRequired": "null",
      "relativePhysicalStats": 0,
      "timeOfDay": null,
      "mustBeTraded": false,
      "evolves": false
    },
    "id": 3
  },
  "baseExperience": 63,
  "genderRateRaw": 0.128,
  "captureRateRaw": 45.0,
  "baseHappiness": 70,
  "hatchCounter": 20,
  "hasMultipleForms": false,
  "growthRate": "mediumSlow",
  "eggGroups": [
    "water1",
    "monster"
  ],
  "learnableMoves": {
    "LevelUp": {
      "Mega Punch": 0,
      "Ice Punch": 0,
      "Mega Kick": 0,
      "Headbutt": 0,
      "Tackle": 1,
      "Body Slam": 0,
      "Take Down": 0,
      "Double Edge": 0,
      "Tail Whip": 4,
      "Bite": 16,
      "Water Gun": 7,
      "Hydro Pump": 40,
      "Bubble Beam": 0,
      "Submission": 0,
      "Counter": 0,
      "Seismic Toss": 0,
      "Strength": 0,
      "Dig": 0,
      "Confusion": 0,
      "Rage": 0,
      "Mimic": 0,
      "Withdraw": 10,
      "Defense Curl": 0,
      "Reflect": 0,
      "Bide": 0,
      "Skull Bash": 31,
      "Bubble": 13,
      "Snore": 0,
      "Curse": 0,
      "Mud Slap": 0,
      "Icy Wind": 0,
      "Endure": 0,
      "Rollout": 0,
      "Dynamic Punch": 0,
      "Rapid Spin": 19,
      "Iron Tail": 0,
      "Rain Dance": 37,
      "Rock Smash": 0,
      "Whirlpool": 0,
      "Focus Punch": 0,
      "Secret Power": 0,
      "Dive": 0,
      "Iron Defense": 34,
      "Water Pulse": 25,
      "Natural Gift": 0,
      "Aqua Tail": 28,
      "Zen Headbutt": 0,
      "Captivate": 0,
      "Power Up Punch": 0
    },
    "Egg": {
      "Mist": 0,
      "Haze": 0,
      "Flail": 0,
      "Foresight": 0,
      "Mirror Coat": 0,
      "Fake Out": 0,
      "Yawn": 0,
      "Refresh": 0,
      "Mud Sport": 0,
      "Water Spout": 0,
      "Muddy Water": 0,
      "Brine": 0,
      "Aqua Ring": 0,
      "Aura Sphere": 0,
      "Dragon Pulse": 0,
      "Aqua Jet": 0
    },
    "Tutor": {
      "Water Pledge": 0
    },
    "Machine": {
      "Surf": 0,
      "Ice Beam": 0,
      "Blizzard": 0,
      "Toxic": 0,
      "Double Team": 0,
      "Waterfall": 0,
      "Rest": 0,
      "Substitute": 0,
      "Protect": 0,
      "Swagger": 0,
      "Attract": 0,
      "Sleep Talk": 0,
      "Return": 0,
      "Frustration": 0,
      "Hidden Power": 0,
      "Hail": 0,
      "Facade": 0,
      "Brick Break": 0,
      "Rock Tomb": 0,
      "Gyro Ball": 0,
      "Fling": 0,
      "Round": 0,
      "Scald": 0,
      "Work Up": 0,
      "Confide": 0
    }
  }
}